pybooklib/__init__.py
pybooklib/pybook_cli.py
pybooklib/pybooklib_cli.py
pybooklib/pylib_cli.py
pybooklib/data/__init__.py
pybooklib/data/about.md
pybooklib/pybook/__init__.py
pybooklib/pybook/main.py
pybooklib/pylib/__init__.py
pybooklib/pylib/main.py
pybooklib/pylib/site.py
pybooklib/pylib/data/__init__.py
pybooklib/pylib/data/index.html
pybooklib-1.2.dist-info/LICENSE
pybooklib-1.2.dist-info/METADATA
pybooklib-1.2.dist-info/WHEEL
pybooklib-1.2.dist-info/entry_points.txt
pybooklib-1.2.dist-info/top_level.txt
pybooklib-1.2.dist-info/RECORD
